{
    "LLNL/RAJAPerf": {
        "languages": {
            "totalCount": 6,
            "totalSize": 35112747,
            "nodes": [
                {
                    "name": "Jupyter Notebook",
                    "color": "#DA5B0B"
                },
                {
                    "name": "C++",
                    "color": "#f34b7d"
                },
                {
                    "name": "Shell",
                    "color": "#89e051"
                },
                {
                    "name": "CMake",
                    "color": "#DA3434"
                },
                {
                    "name": "Python",
                    "color": "#3572A5"
                },
                {
                    "name": "Dockerfile",
                    "color": "#384d54"
                }
            ],
            "edges": [
                {
                    "size": 27438735
                },
                {
                    "size": 7541210
                },
                {
                    "size": 74177
                },
                {
                    "size": 43230
                },
                {
                    "size": 9313
                },
                {
                    "size": 6082
                }
            ]
        }
    }
}